assertpy-stubs/METADATA.toml
assertpy-stubs/__init__.pyi
assertpy-stubs/assertpy.pyi
assertpy-stubs/base.pyi
assertpy-stubs/collection.pyi
assertpy-stubs/contains.pyi
assertpy-stubs/date.pyi
assertpy-stubs/dict.pyi
assertpy-stubs/dynamic.pyi
assertpy-stubs/exception.pyi
assertpy-stubs/extracting.pyi
assertpy-stubs/file.pyi
assertpy-stubs/helpers.pyi
assertpy-stubs/numeric.pyi
assertpy-stubs/py.typed
assertpy-stubs/snapshot.pyi
assertpy-stubs/string.pyi
types_assertpy-1.1.0.20251219.dist-info/licenses/LICENSE
types_assertpy-1.1.0.20251219.dist-info/METADATA
types_assertpy-1.1.0.20251219.dist-info/WHEEL
types_assertpy-1.1.0.20251219.dist-info/top_level.txt
types_assertpy-1.1.0.20251219.dist-info/RECORD
